README.md
setup.py
runpodinfra/__init__.py
runpodinfra/_inputs.py
runpodinfra/_utilities.py
runpodinfra/network_storage.py
runpodinfra/outputs.py
runpodinfra/pod.py
runpodinfra/provider.py
runpodinfra/pulumi-plugin.json
runpodinfra/py.typed
runpodinfra.egg-info/PKG-INFO
runpodinfra.egg-info/SOURCES.txt
runpodinfra.egg-info/dependency_links.txt
runpodinfra.egg-info/not-zip-safe
runpodinfra.egg-info/requires.txt
runpodinfra.egg-info/top_level.txt
runpodinfra/config/__init__.py
runpodinfra/config/vars.py