Metadata-Version: 2.1
Name: runpodinfra
Version: 1.2.7
Summary: The Runpod Pulumi provider provides resources to interact with Runpod's native APIs.
Home-page: https://runpod.io
License: Apache-2.0
Project-URL: Repository, https://github.com/runpod/pulumi-runpod-native
Keywords: pulumi runpod gpus ml ai
Platform: UNKNOWN
Requires-Python: >=3.8
